<?xml version="1.0" encoding="UTF-8"?>
<!DOCTYPE us-patent-grant SYSTEM "us-patent-grant-v45-2014-04-03.dtd" [ ]>
<us-patent-grant lang="EN" dtd-version="v4.5 2014-04-03" file="USD0720566-20150106.XML" status="PRODUCTION" id="us-patent-grant" country="US" date-produced="20141219" date-publ="20150106">
<us-bibliographic-data-grant>
<publication-reference>
<document-id>
<country>US</country>
<doc-number>D0720566</doc-number>
<kind>S1</kind>
<date>20150106</date>
</document-id>
</publication-reference>
<application-reference appl-type="design">
<document-id>
<country>US</country>
<doc-number>29472981</doc-number>
<date>20131118</date>
</document-id>
</application-reference>
<us-application-series-code>29</us-application-series-code>
<us-term-of-grant>
<length-of-grant>14</length-of-grant>
</us-term-of-grant>
<classification-locarno>
<edition>10</edition>
<main-classification>0701</main-classification>
</classification-locarno>
<classification-national>
<country>US</country>
<main-classification>D 73001</main-classification>
<further-classification> D7510</further-classification>
<further-classification> D7517</further-classification>
<further-classification> D9623</further-classification>
<further-classification> D9616</further-classification>
</classification-national>
<invention-title id="d2e53">Cocktail shaker</invention-title>
<us-references-cited>
<us-citation>
<patcit num="00001">
<document-id>
<country>US</country>
<doc-number>D99333</doc-number>
<kind>S</kind>
<name>Rowse</name>
<date>19360400</date>
</document-id>
</patcit>
<category>cited by examiner</category>
<classification-national><country>US</country><main-classification>D 9623</main-classification></classification-national>
</us-citation>
<us-citation>
<patcit num="00002">
<document-id>
<country>US</country>
<doc-number>D150854</doc-number>
<kind>S</kind>
<name>Herrera, Jr.</name>
<date>19480900</date>
</document-id>
</patcit>
<category>cited by examiner</category>
<classification-national><country>US</country><main-classification>D 9616</main-classification></classification-national>
</us-citation>
<us-citation>
<patcit num="00003">
<document-id>
<country>US</country>
<doc-number>D152634</doc-number>
<kind>S</kind>
<name>Mayfield</name>
<date>19490200</date>
</document-id>
</patcit>
<category>cited by examiner</category>
<classification-national><country>US</country><main-classification>D 9619</main-classification></classification-national>
</us-citation>
<us-citation>
<patcit num="00004">
<document-id>
<country>US</country>
<doc-number>D216674</doc-number>
<kind>S</kind>
<name>Saji</name>
<date>19700300</date>
</document-id>
</patcit>
<category>cited by examiner</category>
<classification-national><country>US</country><main-classification>D 9616</main-classification></classification-national>
</us-citation>
<us-citation>
<patcit num="00005">
<document-id>
<country>US</country>
<doc-number>D216867</doc-number>
<kind>S</kind>
<name>Aslin</name>
<date>19700300</date>
</document-id>
</patcit>
<category>cited by examiner</category>
<classification-national><country>US</country><main-classification>D 9619</main-classification></classification-national>
</us-citation>
<us-citation>
<patcit num="00006">
<document-id>
<country>US</country>
<doc-number>D217122</doc-number>
<kind>S</kind>
<name>Segesman</name>
<date>19700400</date>
</document-id>
</patcit>
<category>cited by examiner</category>
<classification-national><country>US</country><main-classification>D 9619</main-classification></classification-national>
</us-citation>
<us-citation>
<patcit num="00007">
<document-id>
<country>US</country>
<doc-number>D217123</doc-number>
<kind>S</kind>
<name>Segesman</name>
<date>19700400</date>
</document-id>
</patcit>
<category>cited by examiner</category>
<classification-national><country>US</country><main-classification>D 9619</main-classification></classification-national>
</us-citation>
<us-citation>
<patcit num="00008">
<document-id>
<country>US</country>
<doc-number>D217124</doc-number>
<kind>S</kind>
<name>Segesman</name>
<date>19700400</date>
</document-id>
</patcit>
<category>cited by examiner</category>
<classification-national><country>US</country><main-classification>D 9619</main-classification></classification-national>
</us-citation>
<us-citation>
<patcit num="00009">
<document-id>
<country>US</country>
<doc-number>D217125</doc-number>
<kind>S</kind>
<name>Segesman</name>
<date>19700400</date>
</document-id>
</patcit>
<category>cited by examiner</category>
<classification-national><country>US</country><main-classification>D 9619</main-classification></classification-national>
</us-citation>
<us-citation>
<patcit num="00010">
<document-id>
<country>US</country>
<doc-number>D217126</doc-number>
<kind>S</kind>
<name>Lammert</name>
<date>19700400</date>
</document-id>
</patcit>
<category>cited by examiner</category>
<classification-national><country>US</country><main-classification>D 9619</main-classification></classification-national>
</us-citation>
<us-citation>
<patcit num="00011">
<document-id>
<country>US</country>
<doc-number>D217127</doc-number>
<kind>S</kind>
<name>Lammert</name>
<date>19700400</date>
</document-id>
</patcit>
<category>cited by examiner</category>
<classification-national><country>US</country><main-classification>D 9619</main-classification></classification-national>
</us-citation>
<us-citation>
<patcit num="00012">
<document-id>
<country>US</country>
<doc-number>D265043</doc-number>
<kind>S</kind>
<name>Wei</name>
<date>19820600</date>
</document-id>
</patcit>
<category>cited by examiner</category>
<classification-national><country>US</country><main-classification>D 73001</main-classification></classification-national>
</us-citation>
<us-citation>
<patcit num="00013">
<document-id>
<country>US</country>
<doc-number>D282339</doc-number>
<kind>S</kind>
<name>Wei</name>
<date>19860100</date>
</document-id>
</patcit>
<category>cited by examiner</category>
<classification-national><country>US</country><main-classification>D 7606</main-classification></classification-national>
</us-citation>
<us-citation>
<patcit num="00014">
<document-id>
<country>US</country>
<doc-number>D289610</doc-number>
<kind>S</kind>
<name>Neyer</name>
<date>19870500</date>
</document-id>
</patcit>
<category>cited by examiner</category>
<classification-national><country>US</country><main-classification>D 9632</main-classification></classification-national>
</us-citation>
<us-citation>
<patcit num="00015">
<document-id>
<country>US</country>
<doc-number>4867214</doc-number>
<kind>A</kind>
<name>Fuller</name>
<date>19890900</date>
</document-id>
</patcit>
<category>cited by examiner</category>
<classification-national><country>US</country><main-classification>428 358</main-classification></classification-national>
</us-citation>
<us-citation>
<patcit num="00016">
<document-id>
<country>US</country>
<doc-number>D309404</doc-number>
<kind>S</kind>
<name>Pierotti</name>
<date>19900700</date>
</document-id>
</patcit>
<category>cited by examiner</category>
<classification-national><country>US</country><main-classification>D 7594</main-classification></classification-national>
</us-citation>
<us-citation>
<patcit num="00017">
<document-id>
<country>US</country>
<doc-number>D309405</doc-number>
<kind>S</kind>
<name>Pierotti</name>
<date>19900700</date>
</document-id>
</patcit>
<category>cited by examiner</category>
<classification-national><country>US</country><main-classification>D 7594</main-classification></classification-national>
</us-citation>
<us-citation>
<patcit num="00018">
<document-id>
<country>US</country>
<doc-number>D327817</doc-number>
<kind>S</kind>
<name>Paullin</name>
<date>19920700</date>
</document-id>
</patcit>
<category>cited by examiner</category>
<classification-national><country>US</country><main-classification>D 7515</main-classification></classification-national>
</us-citation>
<us-citation>
<patcit num="00019">
<document-id>
<country>US</country>
<doc-number>D330857</doc-number>
<kind>S</kind>
<name>Kidd</name>
<date>19921100</date>
</document-id>
</patcit>
<category>cited by examiner</category>
<classification-national><country>US</country><main-classification>D 9451</main-classification></classification-national>
</us-citation>
<us-citation>
<patcit num="00020">
<document-id>
<country>US</country>
<doc-number>D379023</doc-number>
<kind>S</kind>
<name>August</name>
<date>19970400</date>
</document-id>
</patcit>
<category>cited by examiner</category>
<classification-national><country>US</country><main-classification>D99 37</main-classification></classification-national>
</us-citation>
<us-citation>
<patcit num="00021">
<document-id>
<country>US</country>
<doc-number>D379149</doc-number>
<kind>S</kind>
<name>Powell et al.</name>
<date>19970500</date>
</document-id>
</patcit>
<category>cited by examiner</category>
<classification-national><country>US</country><main-classification>D 9451</main-classification></classification-national>
</us-citation>
<us-citation>
<patcit num="00022">
<document-id>
<country>US</country>
<doc-number>6029855</doc-number>
<kind>A</kind>
<name>Adams</name>
<date>20000200</date>
</document-id>
</patcit>
<category>cited by examiner</category>
<classification-national><country>US</country><main-classification>222 78</main-classification></classification-national>
</us-citation>
<us-citation>
<patcit num="00023">
<document-id>
<country>US</country>
<doc-number>D422459</doc-number>
<kind>S</kind>
<name>Webb et al.</name>
<date>20000400</date>
</document-id>
</patcit>
<category>cited by examiner</category>
<classification-national><country>US</country><main-classification>D 7625</main-classification></classification-national>
</us-citation>
<us-citation>
<patcit num="00024">
<document-id>
<country>US</country>
<doc-number>D471060</doc-number>
<kind>S</kind>
<name>Salsman</name>
<date>20030300</date>
</document-id>
</patcit>
<category>cited by examiner</category>
<classification-national><country>US</country><main-classification>D 73921</main-classification></classification-national>
</us-citation>
<us-citation>
<patcit num="00025">
<document-id>
<country>US</country>
<doc-number>D483982</doc-number>
<kind>S</kind>
<name>Irvine</name>
<date>20031200</date>
</document-id>
</patcit>
<category>cited by examiner</category>
<classification-national><country>US</country><main-classification>D 73001</main-classification></classification-national>
</us-citation>
<us-citation>
<patcit num="00026">
<document-id>
<country>US</country>
<doc-number>D507181</doc-number>
<kind>S</kind>
<name>Malik</name>
<date>20050700</date>
</document-id>
</patcit>
<category>cited by examiner</category>
<classification-national><country>US</country><main-classification>D 9451</main-classification></classification-national>
</us-citation>
<us-citation>
<patcit num="00027">
<document-id>
<country>US</country>
<doc-number>D510497</doc-number>
<kind>S</kind>
<name>Hou</name>
<date>20051000</date>
</document-id>
</patcit>
<category>cited by examiner</category>
<classification-national><country>US</country><main-classification>D 73001</main-classification></classification-national>
</us-citation>
<us-citation>
<patcit num="00028">
<document-id>
<country>US</country>
<doc-number>D520654</doc-number>
<kind>S</kind>
<name>Freeman et al.</name>
<date>20060500</date>
</document-id>
</patcit>
<category>cited by examiner</category>
<classification-national><country>US</country><main-classification>D26 16</main-classification></classification-national>
</us-citation>
<us-citation>
<patcit num="00029">
<document-id>
<country>US</country>
<doc-number>D604984</doc-number>
<kind>S</kind>
<name>Kalamaras</name>
<date>20091200</date>
</document-id>
</patcit>
<category>cited by examiner</category>
<classification-national><country>US</country><main-classification>D 73001</main-classification></classification-national>
</us-citation>
<us-citation>
<patcit num="00030">
<document-id>
<country>US</country>
<doc-number>D616169</doc-number>
<kind>S</kind>
<name>Wolford et al.</name>
<date>20100500</date>
</document-id>
</patcit>
<category>cited by examiner</category>
<classification-national><country>US</country><main-classification>D34  4</main-classification></classification-national>
</us-citation>
<us-citation>
<patcit num="00031">
<document-id>
<country>US</country>
<doc-number>D619408</doc-number>
<kind>S</kind>
<name>Hughes et al.</name>
<date>20100700</date>
</document-id>
</patcit>
<category>cited by examiner</category>
<classification-national><country>US</country><main-classification>D 7301</main-classification></classification-national>
</us-citation>
<us-citation>
<patcit num="00032">
<document-id>
<country>US</country>
<doc-number>D629648</doc-number>
<kind>S</kind>
<name>McDonald</name>
<date>20101200</date>
</document-id>
</patcit>
<category>cited by examiner</category>
<classification-national><country>US</country><main-classification>D 7398</main-classification></classification-national>
</us-citation>
<us-citation>
<patcit num="00033">
<document-id>
<country>US</country>
<doc-number>D654752</doc-number>
<kind>S</kind>
<name>Krasner</name>
<date>20120200</date>
</document-id>
</patcit>
<category>cited by examiner</category>
<classification-national><country>US</country><main-classification>D 73001</main-classification></classification-national>
</us-citation>
<us-citation>
<patcit num="00034">
<document-id>
<country>US</country>
<doc-number>D661535</doc-number>
<kind>S</kind>
<name>Hughes et al.</name>
<date>20120600</date>
</document-id>
</patcit>
<category>cited by examiner</category>
<classification-national><country>US</country><main-classification>D 7301</main-classification></classification-national>
</us-citation>
<us-citation>
<patcit num="00035">
<document-id>
<country>US</country>
<doc-number>D661537</doc-number>
<kind>S</kind>
<name>Hughes et al.</name>
<date>20120600</date>
</document-id>
</patcit>
<category>cited by examiner</category>
<classification-national><country>US</country><main-classification>D 7301</main-classification></classification-national>
</us-citation>
<us-citation>
<patcit num="00036">
<document-id>
<country>US</country>
<doc-number>D663575</doc-number>
<kind>S</kind>
<name>Carroll et al.</name>
<date>20120700</date>
</document-id>
</patcit>
<category>cited by examiner</category>
<classification-national><country>US</country><main-classification>D 73921</main-classification></classification-national>
</us-citation>
<us-citation>
<patcit num="00037">
<document-id>
<country>US</country>
<doc-number>D673811</doc-number>
<kind>S</kind>
<name>Roudybush</name>
<date>20130100</date>
</document-id>
</patcit>
<category>cited by examiner</category>
<classification-national><country>US</country><main-classification>D 7510</main-classification></classification-national>
</us-citation>
<us-citation>
<patcit num="00038">
<document-id>
<country>US</country>
<doc-number>D694116</doc-number>
<kind>S</kind>
<name>Spivey</name>
<date>20131100</date>
</document-id>
</patcit>
<category>cited by examiner</category>
<classification-national><country>US</country><main-classification>D 9623</main-classification></classification-national>
</us-citation>
<us-citation>
<patcit num="00039">
<document-id>
<country>US</country>
<doc-number>8701907</doc-number>
<kind>B1</kind>
<name>Mallicoat</name>
<date>20140400</date>
</document-id>
</patcit>
<category>cited by examiner</category>
<classification-national><country>US</country><main-classification>215228</main-classification></classification-national>
</us-citation>
<us-citation>
<patcit num="00040">
<document-id>
<country>US</country>
<doc-number>D710651</doc-number>
<kind>S</kind>
<name>Obioha</name>
<date>20140800</date>
</document-id>
</patcit>
<category>cited by examiner</category>
<classification-national><country>US</country><main-classification>D 7515</main-classification></classification-national>
</us-citation>
</us-references-cited>
<number-of-claims>1</number-of-claims>
<us-exemplary-claim>1</us-exemplary-claim>
<us-field-of-classification-search>
<classification-national>
<country>US</country>
<main-classification>D 7520</main-classification>
</classification-national>
<classification-national>
<country>US</country>
<main-classification>D 7517</main-classification>
</classification-national>
<classification-national>
<country>US</country>
<main-classification>D 73001</main-classification>
</classification-national>
<classification-national>
<country>US</country>
<main-classification>D 7515</main-classification>
</classification-national>
<classification-national>
<country>US</country>
<main-classification>D 7510</main-classification>
</classification-national>
<classification-national>
<country>US</country>
<main-classification>D 7511</main-classification>
</classification-national>
<classification-national>
<country>US</country>
<main-classification>D 7301</main-classification>
</classification-national>
<classification-national>
<country>US</country>
<main-classification>D 7302</main-classification>
</classification-national>
<classification-national>
<country>US</country>
<main-classification>D 7900</main-classification>
</classification-national>
<classification-national>
<country>US</country>
<main-classification>D 7901</main-classification>
</classification-national>
<classification-national>
<country>US</country>
<main-classification>D 7303</main-classification>
</classification-national>
<classification-national>
<country>US</country>
<main-classification>D 9614</main-classification>
</classification-national>
<classification-national>
<country>US</country>
<main-classification>D 9616</main-classification>
</classification-national>
<classification-national>
<country>US</country>
<main-classification>D 9618</main-classification>
</classification-national>
<classification-national>
<country>US</country>
<main-classification>D 9621</main-classification>
</classification-national>
<classification-national>
<country>US</country>
<main-classification>D 9623</main-classification>
</classification-national>
<classification-national>
<country>US</country>
<main-classification>D 9627</main-classification>
</classification-national>
<classification-national>
<country>US</country>
<main-classification>D 9622</main-classification>
</classification-national>
<classification-national>
<country>US</country>
<main-classification>D 9619</main-classification>
</classification-national>
<classification-national>
<country>US</country>
<main-classification>220903</main-classification>
</classification-national>
<classification-national>
<country>US</country>
<main-classification>220703</main-classification>
</classification-national>
<classification-national>
<country>US</country>
<main-classification>215387</main-classification>
</classification-national>
<classification-national>
<country>US</country>
<main-classification>215228</main-classification>
</classification-national>
</us-field-of-classification-search>
<figures>
<number-of-drawing-sheets>6</number-of-drawing-sheets>
<number-of-figures>7</number-of-figures>
</figures>
<us-parties>
<us-applicants>
<us-applicant sequence="001" app-type="applicant" designation="us-only">
<addressbook>
<last-name>Giraldez</last-name>
<first-name>Brandon</first-name>
<address>
<city>Marina Del Rey</city>
<state>CA</state>
<country>US</country>
</address>
</addressbook>
<residence>
<country>US</country>
</residence>
</us-applicant>
</us-applicants>
<inventors>
<inventor sequence="001" designation="us-only">
<addressbook>
<last-name>Giraldez</last-name>
<first-name>Brandon</first-name>
<address>
<city>Marina Del Rey</city>
<state>CA</state>
<country>US</country>
</address>
</addressbook>
</inventor>
</inventors>
<agents>
<agent sequence="01" rep-type="attorney">
<addressbook>
<last-name>Cohen</last-name>
<first-name>Michael N.</first-name>
<address>
<country>unknown</country>
</address>
</addressbook>
</agent>
<agent sequence="02" rep-type="attorney">
<addressbook>
<orgname>Cohen IP Law Group P.C.</orgname>
<address>
<country>unknown</country>
</address>
</addressbook>
</agent>
</agents>
</us-parties>
<examiners>
<primary-examiner>
<last-name>Pandozzi</last-name>
<first-name>Marianne</first-name>
<department>2918</department>
</primary-examiner>
</examiners>
</us-bibliographic-data-grant>
<drawings id="DRAWINGS">
<figure id="Fig-EMI-D00000" num="00000">
<img id="EMI-D00000" he="227.08mm" wi="126.24mm" file="USD0720566-20150106-D00000.TIF" alt="embedded image" img-content="drawing" img-format="tif"/>
</figure>
<figure id="Fig-EMI-D00001" num="00001">
<img id="EMI-D00001" he="247.57mm" wi="125.14mm" file="USD0720566-20150106-D00001.TIF" alt="embedded image" img-content="drawing" img-format="tif"/>
</figure>
<figure id="Fig-EMI-D00002" num="00002">
<img id="EMI-D00002" he="238.93mm" wi="134.03mm" file="USD0720566-20150106-D00002.TIF" alt="embedded image" img-content="drawing" img-format="tif"/>
</figure>
<figure id="Fig-EMI-D00003" num="00003">
<img id="EMI-D00003" he="237.91mm" wi="124.12mm" file="USD0720566-20150106-D00003.TIF" alt="embedded image" img-content="drawing" img-format="tif"/>
</figure>
<figure id="Fig-EMI-D00004" num="00004">
<img id="EMI-D00004" he="239.61mm" wi="126.41mm" file="USD0720566-20150106-D00004.TIF" alt="embedded image" img-content="drawing" img-format="tif"/>
</figure>
<figure id="Fig-EMI-D00005" num="00005">
<img id="EMI-D00005" he="237.24mm" wi="130.73mm" file="USD0720566-20150106-D00005.TIF" alt="embedded image" img-content="drawing" img-format="tif"/>
</figure>
<figure id="Fig-EMI-D00006" num="00006">
<img id="EMI-D00006" he="228.26mm" wi="137.41mm" file="USD0720566-20150106-D00006.TIF" alt="embedded image" img-content="drawing" img-format="tif"/>
</figure>
</drawings>
<description id="description">
<?brief-description-of-drawings description="Brief Description of Drawings" end="lead"?>
<description-of-drawings>
<p id="p-0001" num="0001"><figref idref="DRAWINGS">FIG. 1</figref> is a front perspective view of the cocktail shaker;</p>
<p id="p-0002" num="0002"><figref idref="DRAWINGS">FIG. 2</figref> is a front view of <figref idref="DRAWINGS">FIG. 1</figref>;</p>
<p id="p-0003" num="0003"><figref idref="DRAWINGS">FIG. 3</figref> is a back view of <figref idref="DRAWINGS">FIG. 1</figref>;</p>
<p id="p-0004" num="0004"><figref idref="DRAWINGS">FIG. 4</figref> is a right side view of <figref idref="DRAWINGS">FIG. 1</figref>;</p>
<p id="p-0005" num="0005"><figref idref="DRAWINGS">FIG. 5</figref> is a left side view of <figref idref="DRAWINGS">FIG. 1</figref>;</p>
<p id="p-0006" num="0006"><figref idref="DRAWINGS">FIG. 6</figref> is a top view of <figref idref="DRAWINGS">FIG. 1</figref>; and,</p>
<p id="p-0007" num="0007"><figref idref="DRAWINGS">FIG. 7</figref> is a bottom view of <figref idref="DRAWINGS">FIG. 1</figref>.</p>
</description-of-drawings>
<?brief-description-of-drawings description="Brief Description of Drawings" end="tail"?>
</description>
<us-claim-statement>CLAIM</us-claim-statement>
<claims id="claims">
<claim id="CLM-00001" num="00001">
<claim-text>I claim the ornamental design for the cocktail shaker, as shown and described.</claim-text>
</claim>
</claims>
</us-patent-grant>
