<?xml version="1.0" encoding="UTF-8"?>
<!DOCTYPE us-patent-grant SYSTEM "us-patent-grant-v45-2014-04-03.dtd" [ ]>
<us-patent-grant lang="EN" dtd-version="v4.5 2014-04-03" file="USD0720524-20150106.XML" status="PRODUCTION" id="us-patent-grant" country="US" date-produced="20141219" date-publ="20150106">
<us-bibliographic-data-grant>
<publication-reference>
<document-id>
<country>US</country>
<doc-number>D0720524</doc-number>
<kind>S1</kind>
<date>20150106</date>
</document-id>
</publication-reference>
<application-reference appl-type="design">
<document-id>
<country>US</country>
<doc-number>29427626</doc-number>
<date>20120720</date>
</document-id>
</application-reference>
<us-application-series-code>29</us-application-series-code>
<priority-claims>
<priority-claim sequence="01" kind="national">
<country>CN</country>
<doc-number>2012 3 0017605</doc-number>
<date>20120120</date>
</priority-claim>
</priority-claims>
<us-term-of-grant>
<length-of-grant>14</length-of-grant>
</us-term-of-grant>
<classification-locarno>
<edition>10</edition>
<main-classification>0303</main-classification>
</classification-locarno>
<classification-national>
<country>US</country>
<main-classification>D 3  5</main-classification>
<further-classification> D3 13</further-classification>
</classification-national>
<invention-title id="d2e71">Umbrella</invention-title>
<us-references-cited>
<us-citation>
<patcit num="00001">
<document-id>
<country>US</country>
<doc-number>1952980</doc-number>
<kind>A</kind>
<name>Fox</name>
<date>19340300</date>
</document-id>
</patcit>
<category>cited by examiner</category>
<classification-national><country>US</country><main-classification>135 76</main-classification></classification-national>
</us-citation>
<us-citation>
<patcit num="00002">
<document-id>
<country>US</country>
<doc-number>3281586</doc-number>
<kind>A</kind>
<name>Gonzalez</name>
<date>19661000</date>
</document-id>
</patcit>
<category>cited by examiner</category>
<classification-national><country>US</country><main-classification>362102</main-classification></classification-national>
</us-citation>
<us-citation>
<patcit num="00003">
<document-id>
<country>US</country>
<doc-number>D320600</doc-number>
<kind>S</kind>
<name>Yuen</name>
<date>19911000</date>
</document-id>
</patcit>
<category>cited by examiner</category>
<classification-national><country>US</country><main-classification>D14168</main-classification></classification-national>
</us-citation>
<us-citation>
<patcit num="00004">
<document-id>
<country>US</country>
<doc-number>D347319</doc-number>
<kind>S</kind>
<name>Friedman</name>
<date>19940500</date>
</document-id>
</patcit>
<category>cited by examiner</category>
<classification-national><country>US</country><main-classification>D 3 13</main-classification></classification-national>
</us-citation>
<us-citation>
<patcit num="00005">
<document-id>
<country>US</country>
<doc-number>D353041</doc-number>
<kind>S</kind>
<name>Stenberg</name>
<date>19941200</date>
</document-id>
</patcit>
<category>cited by examiner</category>
<classification-national><country>US</country><main-classification>D 3  5</main-classification></classification-national>
</us-citation>
<us-citation>
<patcit num="00006">
<document-id>
<country>US</country>
<doc-number>D370556</doc-number>
<kind>S</kind>
<name>Yu</name>
<date>19960600</date>
</document-id>
</patcit>
<category>cited by examiner</category>
<classification-national><country>US</country><main-classification>D 3  5</main-classification></classification-national>
</us-citation>
<us-citation>
<patcit num="00007">
<document-id>
<country>US</country>
<doc-number>D415299</doc-number>
<kind>S</kind>
<name>Burbrink</name>
<date>19991000</date>
</document-id>
</patcit>
<category>cited by examiner</category>
<classification-national><country>US</country><main-classification>D26 38</main-classification></classification-national>
</us-citation>
<us-citation>
<patcit num="00008">
<document-id>
<country>US</country>
<doc-number>D430726</doc-number>
<kind>S</kind>
<name>Burbrink</name>
<date>20000900</date>
</document-id>
</patcit>
<category>cited by examiner</category>
<classification-national><country>US</country><main-classification>D 3 13</main-classification></classification-national>
</us-citation>
<us-citation>
<patcit num="00009">
<document-id>
<country>US</country>
<doc-number>6805144</doc-number>
<kind>B2</kind>
<name>Usui et al.</name>
<date>20041000</date>
</document-id>
</patcit>
<category>cited by examiner</category>
<classification-national><country>US</country><main-classification>135 342</main-classification></classification-national>
</us-citation>
<us-citation>
<patcit num="00010">
<document-id>
<country>US</country>
<doc-number>D513117</doc-number>
<kind>S</kind>
<name>Raede</name>
<date>20051200</date>
</document-id>
</patcit>
<category>cited by examiner</category>
<classification-national><country>US</country><main-classification>D 3  5</main-classification></classification-national>
</us-citation>
<us-citation>
<patcit num="00011">
<document-id>
<country>US</country>
<doc-number>D516294</doc-number>
<kind>S</kind>
<name>Olson et al.</name>
<date>20060300</date>
</document-id>
</patcit>
<category>cited by examiner</category>
<classification-national><country>US</country><main-classification>D 3  5</main-classification></classification-national>
</us-citation>
<us-citation>
<patcit num="00012">
<document-id>
<country>US</country>
<doc-number>7706212</doc-number>
<kind>B1</kind>
<name>Campbell</name>
<date>20100400</date>
</document-id>
</patcit>
<category>cited by examiner</category>
<classification-national><country>US</country><main-classification>367116</main-classification></classification-national>
</us-citation>
<us-citation>
<patcit num="00013">
<document-id>
<country>US</country>
<doc-number>D640464</doc-number>
<kind>S</kind>
<name>Forthuber et al.</name>
<date>20110600</date>
</document-id>
</patcit>
<category>cited by examiner</category>
<classification-national><country>US</country><main-classification>D 3  5</main-classification></classification-national>
</us-citation>
<us-citation>
<patcit num="00014">
<document-id>
<country>US</country>
<doc-number>8627839</doc-number>
<kind>B1</kind>
<name>Martinez</name>
<date>20140100</date>
</document-id>
</patcit>
<category>cited by examiner</category>
<classification-national><country>US</country><main-classification>135 66</main-classification></classification-national>
</us-citation>
<us-citation>
<patcit num="00015">
<document-id>
<country>US</country>
<doc-number>D707037</doc-number>
<kind>S</kind>
<name>Tetsuro</name>
<date>20140600</date>
</document-id>
</patcit>
<category>cited by examiner</category>
<classification-national><country>US</country><main-classification>D 3  5</main-classification></classification-national>
</us-citation>
<us-citation>
<patcit num="00016">
<document-id>
<country>US</country>
<doc-number>2003/0131639</doc-number>
<kind>A1</kind>
<name>Segawa</name>
<date>20030700</date>
</document-id>
</patcit>
<category>cited by examiner</category>
<classification-national><country>US</country><main-classification> 70 92</main-classification></classification-national>
</us-citation>
<us-citation>
<patcit num="00017">
<document-id>
<country>US</country>
<doc-number>2005/0121063</doc-number>
<kind>A1</kind>
<name>Chang</name>
<date>20050600</date>
</document-id>
</patcit>
<category>cited by examiner</category>
<classification-national><country>US</country><main-classification>135910</main-classification></classification-national>
</us-citation>
<us-citation>
<patcit num="00018">
<document-id>
<country>US</country>
<doc-number>2008/0041432</doc-number>
<kind>A1</kind>
<name>Willis</name>
<date>20080200</date>
</document-id>
</patcit>
<category>cited by examiner</category>
<classification-national><country>US</country><main-classification>135 74</main-classification></classification-national>
</us-citation>
<us-citation>
<patcit num="00019">
<document-id>
<country>US</country>
<doc-number>2008/0163908</doc-number>
<kind>A1</kind>
<name>O'Kere</name>
<date>20080700</date>
</document-id>
</patcit>
<category>cited by examiner</category>
<classification-national><country>US</country><main-classification>135 16</main-classification></classification-national>
</us-citation>
<us-citation>
<patcit num="00020">
<document-id>
<country>US</country>
<doc-number>2008/0251110</doc-number>
<kind>A1</kind>
<name>Pede</name>
<date>20081000</date>
</document-id>
</patcit>
<category>cited by examiner</category>
<classification-national><country>US</country><main-classification>135 66</main-classification></classification-national>
</us-citation>
</us-references-cited>
<number-of-claims>1</number-of-claims>
<us-exemplary-claim>1</us-exemplary-claim>
<us-field-of-classification-search>
<classification-national>
<country>US</country>
<main-classification>D 3  5</main-classification>
</classification-national>
<classification-national>
<country>US</country>
<main-classification>D 3  6</main-classification>
</classification-national>
<classification-national>
<country>US</country>
<main-classification>D 3 10</main-classification>
</classification-national>
<classification-national>
<country>US</country>
<main-classification>D 3 12</main-classification>
</classification-national>
<classification-national>
<country>US</country>
<main-classification>D 3 13</main-classification>
</classification-national>
<classification-national>
<country>US</country>
<main-classification>135 151</main-classification>
</classification-national>
<classification-national>
<country>US</country>
<main-classification>135 332</main-classification>
</classification-national>
<classification-national>
<country>US</country>
<main-classification>135 201</main-classification>
</classification-national>
<classification-national>
<country>US</country>
<main-classification>135 56</main-classification>
</classification-national>
</us-field-of-classification-search>
<figures>
<number-of-drawing-sheets>10</number-of-drawing-sheets>
<number-of-figures>10</number-of-figures>
</figures>
<us-parties>
<us-applicants>
<us-applicant sequence="001" app-type="applicant" designation="us-only">
<addressbook>
<last-name>Tetsuro</last-name>
<first-name>Tanaka</first-name>
<address>
<city>Kumamoto</city>
<country>JP</country>
</address>
</addressbook>
<residence>
<country>JP</country>
</residence>
</us-applicant>
</us-applicants>
<inventors>
<inventor sequence="001" designation="us-only">
<addressbook>
<last-name>Tetsuro</last-name>
<first-name>Tanaka</first-name>
<address>
<city>Kumamoto</city>
<country>JP</country>
</address>
</addressbook>
</inventor>
</inventors>
<agents>
<agent sequence="01" rep-type="attorney">
<addressbook>
<orgname>Pearne &#x26; Gordon LLP</orgname>
<address>
<country>unknown</country>
</address>
</addressbook>
</agent>
</agents>
</us-parties>
<assignees>
<assignee>
<addressbook>
<orgname>Sprout Co., Ltd</orgname>
<role>03</role>
<address>
<city>Kumamoto</city>
<country>JP</country>
</address>
</addressbook>
</assignee>
</assignees>
<examiners>
<primary-examiner>
<last-name>Windmuller</last-name>
<first-name>John</first-name>
<department>2914</department>
</primary-examiner>
</examiners>
</us-bibliographic-data-grant>
<drawings id="DRAWINGS">
<figure id="Fig-EMI-D00000" num="00000">
<img id="EMI-D00000" he="185.76mm" wi="214.29mm" file="USD0720524-20150106-D00000.TIF" alt="embedded image" img-content="drawing" img-format="tif"/>
</figure>
<figure id="Fig-EMI-D00001" num="00001">
<img id="EMI-D00001" he="170.35mm" wi="167.05mm" file="USD0720524-20150106-D00001.TIF" alt="embedded image" img-content="drawing" img-format="tif"/>
</figure>
<figure id="Fig-EMI-D00002" num="00002">
<img id="EMI-D00002" he="172.97mm" wi="163.41mm" file="USD0720524-20150106-D00002.TIF" alt="embedded image" img-content="drawing" img-format="tif"/>
</figure>
<figure id="Fig-EMI-D00003" num="00003">
<img id="EMI-D00003" he="194.73mm" wi="179.92mm" file="USD0720524-20150106-D00003.TIF" alt="embedded image" img-content="drawing" img-format="tif"/>
</figure>
<figure id="Fig-EMI-D00004" num="00004">
<img id="EMI-D00004" he="184.49mm" wi="166.03mm" file="USD0720524-20150106-D00004.TIF" alt="embedded image" img-content="drawing" img-format="tif"/>
</figure>
<figure id="Fig-EMI-D00005" num="00005">
<img id="EMI-D00005" he="195.41mm" wi="168.99mm" file="USD0720524-20150106-D00005.TIF" alt="embedded image" img-content="drawing" img-format="tif"/>
</figure>
<figure id="Fig-EMI-D00006" num="00006">
<img id="EMI-D00006" he="222.08mm" wi="125.90mm" file="USD0720524-20150106-D00006.TIF" alt="embedded image" img-content="drawing" img-format="tif"/>
</figure>
<figure id="Fig-EMI-D00007" num="00007">
<img id="EMI-D00007" he="217.76mm" wi="123.19mm" file="USD0720524-20150106-D00007.TIF" alt="embedded image" img-content="drawing" img-format="tif"/>
</figure>
<figure id="Fig-EMI-D00008" num="00008">
<img id="EMI-D00008" he="214.80mm" wi="152.23mm" file="USD0720524-20150106-D00008.TIF" alt="embedded image" img-content="drawing" img-format="tif"/>
</figure>
<figure id="Fig-EMI-D00009" num="00009">
<img id="EMI-D00009" he="148.93mm" wi="168.40mm" file="USD0720524-20150106-D00009.TIF" alt="embedded image" img-content="drawing" img-format="tif"/>
</figure>
<figure id="Fig-EMI-D00010" num="00010">
<img id="EMI-D00010" he="203.62mm" wi="139.36mm" file="USD0720524-20150106-D00010.TIF" alt="embedded image" img-content="drawing" img-format="tif"/>
</figure>
</drawings>
<description id="description">
<?brief-description-of-drawings description="Brief Description of Drawings" end="lead"?>
<description-of-drawings>
<p id="p-0001" num="0001"><figref idref="DRAWINGS">FIG. 1</figref> is a front view of an umbrella embodying my new design in a first condition wherein a communication unit is exposed to be visible;</p>
<p id="p-0002" num="0002"><figref idref="DRAWINGS">FIG. 2</figref> is a left side view of the umbrella of <figref idref="DRAWINGS">FIG. 1</figref> in the first condition; the right side view being a mirror image of <figref idref="DRAWINGS">FIG. 2</figref>;</p>
<p id="p-0003" num="0003"><figref idref="DRAWINGS">FIG. 3</figref> is a top view of the umbrella of <figref idref="DRAWINGS">FIG. 1</figref> in the first condition;</p>
<p id="p-0004" num="0004"><figref idref="DRAWINGS">FIG. 4</figref> is a bottom view of the umbrella of <figref idref="DRAWINGS">FIG. 1</figref> in the first condition;</p>
<p id="p-0005" num="0005"><figref idref="DRAWINGS">FIG. 5</figref> is a left perspective view of the umbrella of <figref idref="DRAWINGS">FIG. 1</figref> in the first condition; a right perspective view of the umbrella of <figref idref="DRAWINGS">FIG. 1</figref> in the first condition being a mirror image of <figref idref="DRAWINGS">FIG. 5</figref>;</p>
<p id="p-0006" num="0006"><figref idref="DRAWINGS">FIG. 6</figref> is an enlarged front view of portions of the umbrella shown in <figref idref="DRAWINGS">FIG. 1</figref> in the first condition;</p>
<p id="p-0007" num="0007"><figref idref="DRAWINGS">FIG. 7</figref> is an enlarged left side view of portions of the umbrella shown in <figref idref="DRAWINGS">FIG. 2</figref> in the first condition; an enlarged right side view of portions of the umbrella shown in <figref idref="DRAWINGS">FIG. 2</figref> in the first condition being a mirror image of <figref idref="DRAWINGS">FIG. 7</figref>;</p>
<p id="p-0008" num="0008"><figref idref="DRAWINGS">FIG. 8</figref> is an enlarged left perspective view of portions of the umbrella shown in <figref idref="DRAWINGS">FIG. 5</figref> in the first condition; an enlarged right perspective view of portions of the umbrella shown in <figref idref="DRAWINGS">FIG. 5</figref> in the first condition being a mirror image of <figref idref="DRAWINGS">FIG. 8</figref>;</p>
<p id="p-0009" num="0009"><figref idref="DRAWINGS">FIG. 9</figref> is another front view of the umbrella of <figref idref="DRAWINGS">FIG. 1</figref> in a second condition wherein the communication unit is hidden from view, wherein the umbrella shown in <figref idref="DRAWINGS">FIG. 9</figref> in the second condition has a top view and a bottom view identical to <figref idref="DRAWINGS">FIGS. 3 and 4</figref>, respectively, and the appearance of the umbrella shown in the first condition shown in <figref idref="DRAWINGS">FIGS. 2</figref>, <b>5</b>, <b>7</b> and <b>8</b> represents the umbrella in the second condition but that the communication unit is hidden from view; and,</p>
<p id="p-0010" num="0010"><figref idref="DRAWINGS">FIG. 10</figref> is an enlarged front view of portions of the umbrella similar to <figref idref="DRAWINGS">FIG. 6</figref>, but showing the enlarged front view of the portions of the umbrella in the second condition wherein the communication unit is hidden from view.</p>
</description-of-drawings>
<?brief-description-of-drawings description="Brief Description of Drawings" end="tail"?>
</description>
<us-claim-statement>CLAIM</us-claim-statement>
<claims id="claims">
<claim id="CLM-00001" num="00001">
<claim-text>The ornamental design for an umbrella, as shown and described.</claim-text>
</claim>
</claims>
</us-patent-grant>
